{
  "items": [
    {
      "title": "Home",
      "arg": "18",
      "space_hash": 1,
      "screens_hashes": [
        188980567
      ]
    },
    {
      "title": "Space 2",
      "arg": "19",
      "space_hash": 5,
      "screens_hashes": [
        2077748985
      ]
    },
    {
      "title": "Space 3",
      "arg": "20",
      "space_hash": 4,
      "screens_hashes": [
        2077748985
      ]
    },
    {
      "title": "Space 4",
      "arg": "21",
      "space_hash": 6,
      "screens_hashes": [
        2077748985
      ]
    }
  ]
}
